Metadata-Version: 1.1
Name: maptiler
Version: 1.0.3
Summary: Allows custom geohash bucket sizes and finding buckets in vicinity of given location
Home-page: https://github.com/nziehn/maptiler
Author: Nils Ziehn
Author-email: nziehn@gmail.com
License: MIT
Download-URL: https://github.com/nziehn/maptiler/archive/1.0.3.tar.gz
Keywords: python geohash tiles
Platform: UNKNOWN
